PermutationFeatureSelector/PermutationFeatureSelector.py
PermutationFeatureSelector/__init__.py
PermutationFeatureSelector-0.1.6.dist-info/LICENSE
PermutationFeatureSelector-0.1.6.dist-info/METADATA
PermutationFeatureSelector-0.1.6.dist-info/WHEEL
PermutationFeatureSelector-0.1.6.dist-info/top_level.txt
PermutationFeatureSelector-0.1.6.dist-info/RECORD
