Metadata-Version: 2.1
Name: PermutationFeatureSelector
Version: 0.1.6
Summary: A package for calculating permutation importance and selecting features.
Home-page: https://github.com/Itsuki-2822/PermutationFeatureSelector
Author: Itsuki Ito
Author-email: itoitsuki.28@gmail.com
Classifier: Programming Language :: Python :: 3.9
Classifier: Programming Language :: Python :: 3.10
Classifier: Programming Language :: Python :: 3.11
Classifier: License :: OSI Approved :: MIT License
Classifier: Operating System :: OS Independent
Requires-Python: >=3.9, <4
License-File: LICENSE
Requires-Dist: numpy
Requires-Dist: pandas
Requires-Dist: scikit-learn
Requires-Dist: matplotlib
Requires-Dist: lightgbm
